obc/__init__.py
obc/exceptions.py
obc/providers/__init__.py
obc/providers/base.py
obc/providers/obf.py
obc-2.1.0.dist-info/LICENSE
obc-2.1.0.dist-info/METADATA
obc-2.1.0.dist-info/WHEEL
obc-2.1.0.dist-info/top_level.txt
obc-2.1.0.dist-info/zip-safe
obc-2.1.0.dist-info/RECORD
