Metadata-Version: 2.1
Name: obc
Version: 2.1.0
Summary: The Open Badges Client
Home-page: https://github.com/openfun/open-badges-client
Author: Open FUN (France Universite Numerique)
Author-email: fun.dev@fun-mooc.fr
License: MIT
Keywords: Openbadge,API
Classifier: Development Status :: 5 - Production/Stable
Classifier: Intended Audience :: Developers
Classifier: License :: OSI Approved :: MIT License
Classifier: Natural Language :: English
Classifier: Programming Language :: Python :: 3
Classifier: Programming Language :: Python :: 3.10
Classifier: Programming Language :: Python :: 3.11
Requires-Python: >=3.10
License-File: LICENSE
Requires-Dist: pydantic[email] >=2.0.0
Requires-Dist: httpx >=0.24.1
Provides-Extra: ci
Requires-Dist: twine ==4.0.2 ; extra == 'ci'
Provides-Extra: dev
Requires-Dist: bandit ==1.7.5 ; extra == 'dev'
Requires-Dist: black ==23.11.0 ; extra == 'dev'
Requires-Dist: flake8 ==6.1.0 ; extra == 'dev'
Requires-Dist: isort ==5.12.0 ; extra == 'dev'
Requires-Dist: pydocstyle ==6.3.0 ; extra == 'dev'
Requires-Dist: pylint ==3.0.2 ; extra == 'dev'
Requires-Dist: pytest ==7.4.3 ; extra == 'dev'
Requires-Dist: pytest-cov ==4.1.0 ; extra == 'dev'
Requires-Dist: pytest-httpx ==0.27.0 ; extra == 'dev'
Requires-Dist: responses ==0.24.1 ; extra == 'dev'
